TensorflowZeroToAll/README.md
TensorflowZeroToAll/__init__.py
TensorflowZeroToAll/__main__.py
TensorflowZeroToAll/file.epub
TensorflowZeroToAll/index.html
TensorflowZeroToAll/css/__init__.py
TensorflowZeroToAll/css/annotations.css
TensorflowZeroToAll/css/main.css
TensorflowZeroToAll/css/normalize.css
TensorflowZeroToAll/css/popup.css
TensorflowZeroToAll/font/__init__.py
TensorflowZeroToAll/font/fontello.eot
TensorflowZeroToAll/font/fontello.svg
TensorflowZeroToAll/font/fontello.ttf
TensorflowZeroToAll/font/fontello.woff
TensorflowZeroToAll/img/__init__.py
TensorflowZeroToAll/img/annotator-glyph-sprite.png
TensorflowZeroToAll/img/annotator-icon-sprite.png
TensorflowZeroToAll/img/apple-touch-icon.png
TensorflowZeroToAll/img/cancelfullscreen.png
TensorflowZeroToAll/img/close.png
TensorflowZeroToAll/img/fullscreen.png
TensorflowZeroToAll/img/loader.gif
TensorflowZeroToAll/img/menu-icon.png
TensorflowZeroToAll/img/save.png
TensorflowZeroToAll/img/saved.png
TensorflowZeroToAll/img/settings-s.png
TensorflowZeroToAll/img/settings.png
TensorflowZeroToAll/img/star.png
TensorflowZeroToAll/js/__init__.py
TensorflowZeroToAll/js/epub.js
TensorflowZeroToAll/js/epub.min.js
TensorflowZeroToAll/js/epub.min.map
TensorflowZeroToAll/js/hooks.min.js
TensorflowZeroToAll/js/hooks.min.map
TensorflowZeroToAll/js/reader.js
TensorflowZeroToAll/js/reader.js.map
TensorflowZeroToAll/js/reader.min.js
TensorflowZeroToAll/js/reader.min.map
TensorflowZeroToAll/js/hooks/__init__.py
TensorflowZeroToAll/js/hooks/extensions/__init__.py
TensorflowZeroToAll/js/hooks/extensions/highlight.js
TensorflowZeroToAll/js/libs/__init__.py
TensorflowZeroToAll/js/libs/jquery.min.js
TensorflowZeroToAll/js/libs/localforage.min.js
TensorflowZeroToAll/js/libs/screenfull.js
TensorflowZeroToAll/js/libs/screenfull.min.js
TensorflowZeroToAll/js/libs/zip.min.js
TensorflowZeroToAll/js/plugins/__init__.py
TensorflowZeroToAll/js/plugins/hypothesis.js
TensorflowZeroToAll/js/plugins/search.js
tensorflow_zero_to_all-2024.3.3.0.dist-info/METADATA
tensorflow_zero_to_all-2024.3.3.0.dist-info/WHEEL
tensorflow_zero_to_all-2024.3.3.0.dist-info/entry_points.txt
tensorflow_zero_to_all-2024.3.3.0.dist-info/top_level.txt
tensorflow_zero_to_all-2024.3.3.0.dist-info/RECORD
